skills_cli/__init__.py
skills_cli/cli.py
skills_cli-0.1.1.dist-info/METADATA
skills_cli-0.1.1.dist-info/WHEEL
skills_cli-0.1.1.dist-info/entry_points.txt
skills_cli-0.1.1.dist-info/top_level.txt
skills_cli-0.1.1.dist-info/RECORD
