Metadata-Version: 2.4
Name: skills-cli
Version: 0.1.1
Summary: A CLI tool for managing skills.
Author-email: Ben Anderson <ben@trytaylor.ai>
License-Expression: MIT
Requires-Python: >=3.12
Requires-Dist: pyyaml>=6.0
Requires-Dist: httpx>=0.27
